cdk_circleci_oidc/__init__.py
cdk_circleci_oidc/py.typed
cdk_circleci_oidc/_jsii/__init__.py
cdk_circleci_oidc/_jsii/cdk-circleci-oidc@1.0.2.jsii.tgz
cdk_circleci_oidc-1.0.2.dist-info/LICENSE
cdk_circleci_oidc-1.0.2.dist-info/METADATA
cdk_circleci_oidc-1.0.2.dist-info/WHEEL
cdk_circleci_oidc-1.0.2.dist-info/top_level.txt
cdk_circleci_oidc-1.0.2.dist-info/RECORD
